LICENSE
MANIFEST.in
README.md
requirements.txt
setup.py
scrapesession/__init__.py
scrapesession/__main__.py
scrapesession/cookie_policy.py
scrapesession/functions.py
scrapesession/playwright.py
scrapesession/scrapesession.py
scrapesession/session.py
scrapesession.egg-info/PKG-INFO
scrapesession.egg-info/SOURCES.txt
scrapesession.egg-info/dependency_links.txt
scrapesession.egg-info/entry_points.txt
scrapesession.egg-info/not-zip-safe
scrapesession.egg-info/requires.txt
scrapesession.egg-info/top_level.txt
tests/__init__.py
tests/scrapesession_test.py