Metadata-Version: 2.1
Name: scrapesession
Version: 0.0.13
Summary: A library for processing image features in a dataframe.
Home-page: https://github.com/8W9aG/scrapesession
Author: Will Sackfield
Author-email: will.sackfield@gmail.com
License: MIT
Keywords: session,scraping
Classifier: License :: OSI Approved :: MIT License
Classifier: Programming Language :: Python :: 3
License-File: LICENSE
Requires-Dist: numpy>=1.26.4
Requires-Dist: requests_cache>=1.2.1
Requires-Dist: wayback>=0.4.5
Requires-Dist: func-timeout>=4.3.5
Requires-Dist: random_user_agent>=1.0.1
Requires-Dist: tenacity>=9.1.2
Requires-Dist: playwright>=1.53.0
